stackility/CloudStackUtility.py
stackility/__init__.py
stackility/command.py
stackility/drift.py
stackility/stack_tool.py
Stackility-0.7.4.dist-info/LICENSE
Stackility-0.7.4.dist-info/METADATA
Stackility-0.7.4.dist-info/WHEEL
Stackility-0.7.4.dist-info/entry_points.txt
Stackility-0.7.4.dist-info/top_level.txt
Stackility-0.7.4.dist-info/RECORD
