Metadata-Version: 2.1
Name: Stackility
Version: 0.7.4
Summary: Python CloudFormation utility
Home-page: https://github.com/muckamuck/stackility
Author: Chuck Muckamuck
Author-email: Chuck.Muckamuck@gmail.com
License: UNKNOWN
Platform: UNKNOWN
Requires-Dist: boto3 (>=1.4.3)
Requires-Dist: requests (>=2.18)
Requires-Dist: Click (>=6.7)
Requires-Dist: PyYAML (>=3.12)
Requires-Dist: pymongo (>=3.4.0)
Requires-Dist: tabulate (>=0.8)
Requires-Dist: configparser
Requires-Dist: jinja2
Requires-Dist: cloudformation-validator (>=0.6)
